README.md
setup.py
leiden_clustering/LeidenClustering.py
leiden_clustering/__init__.py
leiden_clustering.egg-info/PKG-INFO
leiden_clustering.egg-info/SOURCES.txt
leiden_clustering.egg-info/dependency_links.txt
leiden_clustering.egg-info/requires.txt
leiden_clustering.egg-info/top_level.txt