Metadata-Version: 1.2
Name: leiden-clustering
Version: 0.1.0
Summary: Cluster your data matrix with the Leiden algorithm.
Home-page: https://github.com/MiqG/leiden_clustering
Author: Miquel Anglada Girotto
Author-email: miquelangladagirotto@gmail.com
License: BSD 3-Clause License
Project-URL: Issues, https://github.com/MiqG/leiden_clustering/issues
Platform: UNKNOWN
Classifier: License :: OSI Approved :: BSD License
Classifier: Topic :: System :: Clustering
Requires-Python: >=3.7
